LICENSE
MANIFEST.in
README.md
setup.cfg
setup.py
EllucianEthosPythonClient/ChangeNotificationMessage.py
EllucianEthosPythonClient/ChangeNotificationUtils.py
EllucianEthosPythonClient/EllucianEthosAPIClient.py
EllucianEthosPythonClient/EthosChangeNotificationPollerThread.py
EllucianEthosPythonClient/EthosLoginSession.py
EllucianEthosPythonClient/ListBasedResourceIterator.py
EllucianEthosPythonClient/ResourceIterator.py
EllucianEthosPythonClient/WorkerThread.py
EllucianEthosPythonClient/__init__.py
EllucianEthosPythonClient/_version.py
EllucianEthosPythonClient.egg-info/PKG-INFO
EllucianEthosPythonClient.egg-info/SOURCES.txt
EllucianEthosPythonClient.egg-info/dependency_links.txt
EllucianEthosPythonClient.egg-info/not-zip-safe
EllucianEthosPythonClient.egg-info/requires.txt
EllucianEthosPythonClient.egg-info/top_level.txt
EllucianEthosPythonClient/ResourceWrappers/BaseResourceWrapper.py
EllucianEthosPythonClient/ResourceWrappers/ResPersons.py
EllucianEthosPythonClient/ResourceWrappers/ResourceWrapperFactory.py
EllucianEthosPythonClient/ResourceWrappers/__init__.py