Metadata-Version: 2.1
Name: EllucianEthosPythonClient
Version: 0.2.19
Summary: Python package which provides Ellucian Ethos Client
Home-page: https://github.com/rmetcalf9/EllucianEthosPythonClient
Author: Robert Metcalf
Author-email: rmetcalf9@googlemail.com
License: MIT
Platform: UNKNOWN
License-File: LICENSE
